mkdocs_pandoc/__init__.py
mkdocs_pandoc/plugin.py
mkdocs_pandoc/renderer.py
mkdocs_pandoc/utils.py
mkdocs_pandoc_plugin-1.0.1.dist-info/LICENSE.md
mkdocs_pandoc_plugin-1.0.1.dist-info/METADATA
mkdocs_pandoc_plugin-1.0.1.dist-info/WHEEL
mkdocs_pandoc_plugin-1.0.1.dist-info/entry_points.txt
mkdocs_pandoc_plugin-1.0.1.dist-info/top_level.txt
mkdocs_pandoc_plugin-1.0.1.dist-info/RECORD
