Metadata-Version: 2.1
Name: mkdocs-pandoc-plugin
Version: 1.0.1
Summary: An MkDocs plugin to export content pages to any files that pandoc can handle
Home-page: https://github.com/alexandre-perrin/mkdocs-pandoc-plugin
Author: Alexandre, Perrin
Author-email: alexandreperr@gmail.com
License: MIT
Keywords: mkdocs pandoc export
Platform: UNKNOWN
Classifier: Development Status :: 4 - Beta
Classifier: Intended Audience :: Developers
Classifier: Intended Audience :: Information Technology
Classifier: License :: OSI Approved :: MIT License
Classifier: Programming Language :: Python
Classifier: Programming Language :: Python :: 3 :: Only
Classifier: Programming Language :: Python :: 3.4
Classifier: Programming Language :: Python :: 3.5
Classifier: Programming Language :: Python :: 3.6
Classifier: Programming Language :: Python :: 3.7
Requires-Python: >=3.4
Requires-Dist: mkdocs
Requires-Dist: beautifulsoup4
